scematk/__init__.py
scematk/py.typed
scematk/version.py
scematk/annotate/__init__.py
scematk/annotate/_annotate.py
scematk/annotate/_circle.py
scematk/annotate/_rectangle.py
scematk/cluster/__init__.py
scematk/cluster/_quick_connect.py
scematk/cluster/profiles/__init__.py
scematk/cluster/profiles/_eddie.py
scematk/cluster/profiles/_get_profile.py
scematk/data/__init__.py
scematk/data/_download_example.py
scematk/deconvolve/__init__.py
scematk/deconvolve/_native_skimage.py
scematk/deconvolve/_stain_deconvolver.py
scematk/image/__init__.py
scematk/image/_binary_mask.py
scematk/image/_image.py
scematk/image/_label_mask.py
scematk/image/_mask.py
scematk/image/_ubyte_image.py
scematk/io/__init__.py
scematk/io/_read_zarr_bin_mask.py
scematk/io/_read_zarr_lbl_mask.py
scematk/io/_read_zarr_ubimg.py
scematk/io/_tiff_to_zarr.py
scematk/module/_module.py
scematk/morphology/__init__.py
scematk/morphology/_morphological_profiler.py
scematk/morphology/_modules/_abc_module.py
scematk/morphology/_modules/_areashape_module.py
scematk/morphology/_modules/_default_module.py
scematk/morphology/_modules/_intensity_module.py
scematk/process/__init__.py
scematk/process/_process.py
scematk/process/colour/__init__.py
scematk/process/colour/_rgb_to_grey.py
scematk/process/contrast/__init__.py
scematk/process/contrast/_gamma_contrast.py
scematk/process/contrast/_linear_contrast.py
scematk/process/contrast/_min_max_contrast.py
scematk/process/dask/__init__.py
scematk/process/dask/_rechunk.py
scematk/process/filter/__init__.py
scematk/process/filter/_distribution_filters.py
scematk/process/filter/_gaussian_blur.py
scematk/process/morphology/__init__.py
scematk/process/morphology/_binary_closing.py
scematk/process/morphology/_binary_opening.py
scematk/segment/__init__.py
scematk/segment/_clip_mask.py
scematk/segment/_segmenter.py
scematk/segment/primary/_stardist.py
scematk/segment/secondary/__init__.py
scematk/segment/secondary/_expansion_segmenter.py
scematk-0.0.3.dist-info/LICENSE
scematk-0.0.3.dist-info/METADATA
scematk-0.0.3.dist-info/WHEEL
scematk-0.0.3.dist-info/top_level.txt
scematk-0.0.3.dist-info/RECORD
