Metadata-Version: 2.1
Name: scematk
Version: 0.0.3
Author-email: Hugh Warden <hugh.warden@outlook.com>
License: Apache License
Project-URL: Homepage, https://github.com/SCEMA-WSI/scematk
Project-URL: Repository, https://github.com/SCEMA-WSI/scematk
Project-URL: Changelog, https://github.com/SCEMA-WSI/scematk/blob/main/CHANGELOG.md
Classifier: Intended Audience :: Science/Research
Classifier: Development Status :: 3 - Alpha
Classifier: License :: OSI Approved :: Apache Software License
Classifier: Programming Language :: Python :: 3
Classifier: Topic :: Scientific/Engineering :: Artificial Intelligence
Requires-Python: >=3.8
License-File: LICENSE
Requires-Dist: csbdeep >=0.6.0
Requires-Dist: dask >=2021.6.0
Requires-Dist: dask-image >=0.6.0
Requires-Dist: dask-jobqueue >=0.7.0
Requires-Dist: matplotlib >=3.4.3
Requires-Dist: matplotlib-scalebar >=0.7.2
Requires-Dist: numpy >=1.20.0
Requires-Dist: openslide-python >=1.1.2
Requires-Dist: requests >=2.26.0
Requires-Dist: scikit-image >=0.18.3
Requires-Dist: shapely >=1.7.1
Requires-Dist: stardist >=0.6.0
Requires-Dist: tensorflow >=2.6.0
Requires-Dist: tqdm >=4.62.3
Requires-Dist: zarr >=2.10.0
Provides-Extra: dev
Requires-Dist: ruff ; extra == 'dev'
Requires-Dist: mypy <1.11,>=1.0 ; extra == 'dev'
Requires-Dist: black <25.0,>=23.0 ; extra == 'dev'
Requires-Dist: isort <5.14,>=5.12 ; extra == 'dev'
Requires-Dist: pytest ; extra == 'dev'
Requires-Dist: pytest-sphinx ; extra == 'dev'
Requires-Dist: pytest-cov ; extra == 'dev'
Requires-Dist: twine >=1.11.0 ; extra == 'dev'
Requires-Dist: build ; extra == 'dev'
Requires-Dist: setuptools ; extra == 'dev'
Requires-Dist: wheel ; extra == 'dev'
Requires-Dist: Sphinx <7.4.0,>=4.3.0 ; extra == 'dev'
Requires-Dist: furo ==2024.5.6 ; extra == 'dev'
Requires-Dist: myst-parser <3.1,>=1.0 ; extra == 'dev'
Requires-Dist: sphinx-copybutton ==0.5.2 ; extra == 'dev'
Requires-Dist: sphinx-autobuild ==2021.3.14 ; extra == 'dev'
Requires-Dist: sphinx-autodoc-typehints ==1.23.3 ; extra == 'dev'
Requires-Dist: packaging ; extra == 'dev'
